deepsmiles/__init__.py
deepsmiles/converter.py
deepsmiles/decode.py
deepsmiles/encode.py
deepsmiles/exceptions.py
deepsmiles/testsuite.py
deepsmiles-1.0.1.dist-info/METADATA
deepsmiles-1.0.1.dist-info/RECORD
deepsmiles-1.0.1.dist-info/WHEEL
deepsmiles-1.0.1.dist-info/top_level.txt
