Metadata-Version: 2.1
Name: deepsmiles
Version: 1.0.1
Summary: DeepSMILES, a SMILES-like syntax suited to machine learning
Home-page: http://github.com/nextmovesoftware/deepsmiles
Author: Noel M O'Boyle
Author-email: noel@nextmovesoftware.com
License: License :: OSI Approved :: MIT License
Platform: any
Classifier: Development Status :: 5 - Production/Stable
Classifier: Intended Audience :: Developers
Classifier: Natural Language :: English
Classifier: Operating System :: OS Independent
Classifier: Programming Language :: Python
